myframework/__init__.py
myframework/module1.py
myframework/module2.py
myframework/utils.py
tests/__init__.py
tests/conftest.py
tests/test_module1.py
tests/test_module2.py
ahsentahir_myframework-0.1.0.dist-info/LICENSE
ahsentahir_myframework-0.1.0.dist-info/METADATA
ahsentahir_myframework-0.1.0.dist-info/WHEEL
ahsentahir_myframework-0.1.0.dist-info/top_level.txt
ahsentahir_myframework-0.1.0.dist-info/RECORD
